MANIFEST.in
README.rst
setup.cfg
setup.py
vstat/__init__.py
vstat/vstat.py
vstat.egg-info/PKG-INFO
vstat.egg-info/SOURCES.txt
vstat.egg-info/dependency_links.txt
vstat.egg-info/not-zip-safe
vstat.egg-info/requires.txt
vstat.egg-info/top_level.txt