Metadata-Version: 1.0
Name: vstat
Version: 0.2
Summary: Implementation of the v-statistic
Home-page: https://github.com/dostodabsi/vstat.py
Author: Fabian Dablander
Author-email: dostodabsi@gmail.com
License: MIT
Platform: UNKNOWN
